{
  "fund_code": "000042",
  "update_time": "2026-02-17T15:03:02.579370",
  "基金代码": "000042",
  "基金名称": "中证财通可持续发展100指数",
  "基金全称": "中证财通中国可持续发展100(ECPI ESG)指数增强型证券投资基金",
  "成立时间": "2013-03-22",
  "最新规模": "3426.46万",
  "基金公司": "财通基金管理有限公司",
  "基金经理": "顾弘原",
  "托管银行": "上海银行股份有限公司",
  "基金类型": "股票型-增强指数",
  "评级机构": "<NA>",
  "基金评级": "暂无评级",
  "投资策略": "本基金采取“指数化投资为主、主动性投资为辅”的投资策略，力求在控制标的指数跟踪误差的基础上，适当采用量化增强策略获取超越标的指数的投资收益。",
  "投资目标": "本基金为股票指数增强型基金，在力求对中证财通中国可持续发展100（ECPI ESG）指数进行有效跟踪的基础上，通过基于数量化的多策略系统进行收益增强和风险控制，力争实现超越该指数的收益率水平。\r\n    本基金对业绩比较基准的跟踪目标是：力争使基金净值增长率与业绩比较基准之间的日均跟踪偏离度的绝对值不超过0.5%，年化跟踪误差不超过7.75%。",
  "业绩比较基准": "中证财通中国可持续发展100（ECPI ESG）指数收益率×95%+银行活期存款利率（税后）×5%"
}